django_xss_fuzzer/__init__.py
django_xss_fuzzer/pytest_plugin.py
django_xss_fuzzer-0.3.1.dist-info/entry_points.txt
django_xss_fuzzer-0.3.1.dist-info/LICENSE
django_xss_fuzzer-0.3.1.dist-info/WHEEL
django_xss_fuzzer-0.3.1.dist-info/METADATA
django_xss_fuzzer-0.3.1.dist-info/RECORD
