Metadata-Version: 2.1
Name: django-xss-fuzzer
Version: 0.3.1
Summary: django-xss-fuzzer: An XSS vulnerability fuzz tester for Django views.
Home-page: https://github.com/tonybaloney/django-xss-fuzzer
License: UNKNOWN
Keywords: django,xss,security,testing
Author: Anthony Shaw
Author-email: anthonyshaw@apache.org
Requires-Python: >=3.5
Classifier: License :: OSI Approved :: Apache Software License
Classifier: Framework :: Pytest
Requires-Dist: Django >= 2.0
Requires-Dist: pytest >= 5.0.0 ; extra == "test"
Requires-Dist: pytest-django ; extra == "test"
Requires-Dist: selenium ; extra == "test"
Requires-Dist: pytest-selenium ; extra == "test"
Requires-Dist: pytest-pythonpath ; extra == "test"
Provides-Extra: test
